tunestudio/__init__.py
tunestudio/config.py
tunestudio/data_loader.py
tunestudio/main.py
tunestudio/model_manager.py
tunestudio/trainer.py
tunestudio/static/assets/index-9yfeewAT.js
tunestudio/static/assets/index-DsEUNvFU.css
tunestudio/templates/index.html
tunestudio-0.0.11.dist-info/licenses/LICENSE
tunestudio-0.0.11.dist-info/METADATA
tunestudio-0.0.11.dist-info/WHEEL
tunestudio-0.0.11.dist-info/entry_points.txt
tunestudio-0.0.11.dist-info/top_level.txt
tunestudio-0.0.11.dist-info/RECORD
