Metadata-Version: 2.4
Name: tunestudio
Version: 0.0.11
Summary: An all in one platform for finetuning your LLM models using your Google Colab, Kaggle or Local resources.
Home-page: https://github.com/ankitdutta428/tunestudio
Author: Minerva AI
Author-email: services.ai.minerva@gmail.com
Keywords: machine-learning,llm,fine-tuning,transformers,no-code,ui,tunestudio
Classifier: Development Status :: 3 - Alpha
Classifier: Intended Audience :: Developers
Classifier: Intended Audience :: Science/Research
Classifier: Topic :: Scientific/Engineering :: Artificial Intelligence
Classifier: License :: OSI Approved :: MIT License
Classifier: Programming Language :: Python :: 3
Classifier: Programming Language :: Python :: 3.8
Classifier: Programming Language :: Python :: 3.9
Classifier: Programming Language :: Python :: 3.10
Classifier: Programming Language :: Python :: 3.11
Requires-Python: >=3.8
License-File: LICENSE
Requires-Dist: flask>=2.0.0
Requires-Dist: flask-cors>=4.0.0
Requires-Dist: pandas>=1.3.0
Requires-Dist: transformers>=4.20.0
Requires-Dist: torch>=1.12.0
Requires-Dist: pyngrok>=6.0.0
Requires-Dist: huggingface-hub>=0.10.0
Requires-Dist: datasets>=2.0.0
Requires-Dist: accelerate>=0.20.0
Provides-Extra: dev
Requires-Dist: pytest>=7.0.0; extra == "dev"
Requires-Dist: black>=22.0.0; extra == "dev"
Requires-Dist: flake8>=4.0.0; extra == "dev"
Dynamic: author
Dynamic: author-email
Dynamic: classifier
Dynamic: description
Dynamic: description-content-type
Dynamic: home-page
Dynamic: keywords
Dynamic: license-file
Dynamic: provides-extra
Dynamic: requires-dist
Dynamic: requires-python
Dynamic: summary
